Metadata-Version: 2.1
Name: django-clearcache
Version: 1.2.0
Summary: Allows you to clear Django cache via admin UI or manage.py command
Home-page: https://timonweb.com
License: MIT
Keywords: django,cache
Author: Tim Kamanin
Author-email: tim@timonweb.com
Requires-Python: >=3.7
Classifier: Development Status :: 5 - Production/Stable
Classifier: Environment :: Web Environment
Classifier: Framework :: Django
Classifier: Framework :: Django :: 2.2
Classifier: Framework :: Django :: 3.0
Classifier: Framework :: Django :: 3.1
Classifier: Framework :: Django :: 3.2
Classifier: Intended Audience :: Developers
Classifier: License :: OSI Approved :: MIT License
Classifier: Operating System :: OS Independent
Classifier: Programming Language :: Python :: 3
Classifier: Programming Language :: Python :: 3.7
Classifier: Programming Language :: Python :: 3.8
Classifier: Programming Language :: Python :: 3.9
Classifier: Topic :: Software Development :: Libraries
Classifier: Topic :: Utilities
Requires-Dist: django (>=2.2)
Project-URL: Repository, https://github.com/timonweb/django-clearcache
